gdmec23120148/__init__.py
gdmec23120148-0.1.1.dist-info/METADATA
gdmec23120148-0.1.1.dist-info/WHEEL
gdmec23120148-0.1.1.dist-info/entry_points.txt
gdmec23120148-0.1.1.dist-info/RECORD
